mstdbscan/__init__.py
mstdbscan/diffusionZone.py
mstdbscan/directedEdge.py
mstdbscan/edgeWeightedDigraph.py
mstdbscan/mstdbscanCoreAlgorithm.py
mstdbscan/mstdbscanGear.py
mstdbscan/mstdbscanMainInterface.py
mstdbscan/mstdbscanResult.py
mstdbscan/transmissionCluster.py
mstdbscan/weightedQuickUnionDictionary.py
mstdbscan-0.1.2.dist-info/METADATA
mstdbscan-0.1.2.dist-info/WHEEL
mstdbscan-0.1.2.dist-info/top_level.txt
mstdbscan-0.1.2.dist-info/RECORD
