Metadata-Version: 2.1
Name: mstdbscan
Version: 0.1.2
Summary: An algorithm for space-time transmission clustering.
Home-page: UNKNOWN
Author: Fei-Ying Felix Kuo
Author-email: fykuofelix@gmail.com
License: UNKNOWN
Keywords: MST_DBSCAN,Space-time,transmission,cluster
Platform: UNKNOWN
Requires-Dist: pandas
Requires-Dist: geopandas
Requires-Dist: python-louvain
Requires-Dist: numpy
Requires-Dist: scipy
Requires-Dist: shapely
Requires-Dist: imageio
